AUTHORS.rst
CONTRIBUTING.rst
HISTORY.rst
LICENSE
MANIFEST.in
README.rst
setup.cfg
setup.py
docs/Makefile
docs/authors.rst
docs/conf.py
docs/contributing.rst
docs/history.rst
docs/index.rst
docs/installation.rst
docs/make.bat
docs/readme.rst
docs/usage.rst
relask/__init__.py
relask/app.py
relask/babelRelayPlugin.js
relask/cli.py
relask/jwt.py
relask/package.json
relask/relask.js
relask.egg-info/PKG-INFO
relask.egg-info/SOURCES.txt
relask.egg-info/dependency_links.txt
relask.egg-info/entry_points.txt
relask.egg-info/not-zip-safe
relask.egg-info/requires.txt
relask.egg-info/top_level.txt
relask/templates/relask/index.html
tests/__init__.py
tests/test_relask.py