Metadata-Version: 1.1
Name: relask
Version: 0.1.0
Summary: A Relay-based web development kit on Flask
Home-page: https://github.com/decentfox/relask
Author: Fantix King
Author-email: fantix.king@gmail.com
License: BSD license
Keywords: relask
Platform: UNKNOWN
Classifier: Development Status :: 2 - Pre-Alpha
Classifier: Intended Audience :: Developers
Classifier: License :: OSI Approved :: BSD License
Classifier: Natural Language :: English
Classifier: Programming Language :: Python :: 3
Classifier: Programming Language :: Python :: 3.5
